README.md
fuckpy3.py
setup.py
fuckpy3.egg-info/PKG-INFO
fuckpy3.egg-info/SOURCES.txt
fuckpy3.egg-info/dependency_links.txt
fuckpy3.egg-info/top_level.txt