Metadata-Version: 1.0
Name: fuckpy3
Version: 1.0
Summary: Some much-needed sanity for byte-wrangling in python3.
Home-page: https://github.com/zardus/fuckpy3
Author: UNKNOWN
Author-email: UNKNOWN
License: UNKNOWN
Platform: UNKNOWN
